{
  "gitSyncId": "67d467378041415203d192d8_802efe9d-15bf-4676-9a9d-6175faf12815",
  "unpublishedPage": {
    "isHidden": false,
    "layouts": [
      {
        "dsl": {
          "backgroundColor": "none",
          "bottomRow": 850,
          "canExtend": true,
          "containerStyle": "none",
          "detachFromLayout": true,
          "dynamicBindingPathList": [],
          "leftColumn": 0,
          "minHeight": 690,
          "parentColumnSpace": 1,
          "parentRowSpace": 1,
          "rightColumn": 1224,
          "snapColumns": 64,
          "snapRows": 67,
          "topRow": 0,
          "type": "CANVAS_WIDGET",
          "version": 92,
          "widgetId": "0",
          "widgetName": "MainContainer"
        }
      }
    ],
    "name": "Badminton",
    "slug": "badminton"
  }
}